hierarchical_storage/__init__.py
hierarchical_storage/hierarchical_node.py
hierarchical_storage/hierarchical_node_mismatch_exception.py
hierarchical_storage-1.0.dist-info/METADATA
hierarchical_storage-1.0.dist-info/WHEEL
hierarchical_storage-1.0.dist-info/top_level.txt
hierarchical_storage-1.0.dist-info/RECORD
